Pyqt5ZhongwenJiaocheng/README.md
Pyqt5ZhongwenJiaocheng/__init__.py
Pyqt5ZhongwenJiaocheng/__main__.py
Pyqt5ZhongwenJiaocheng/file.epub
Pyqt5ZhongwenJiaocheng/index.html
Pyqt5ZhongwenJiaocheng/css/__init__.py
Pyqt5ZhongwenJiaocheng/css/annotations.css
Pyqt5ZhongwenJiaocheng/css/main.css
Pyqt5ZhongwenJiaocheng/css/normalize.css
Pyqt5ZhongwenJiaocheng/css/popup.css
Pyqt5ZhongwenJiaocheng/font/__init__.py
Pyqt5ZhongwenJiaocheng/font/fontello.eot
Pyqt5ZhongwenJiaocheng/font/fontello.svg
Pyqt5ZhongwenJiaocheng/font/fontello.ttf
Pyqt5ZhongwenJiaocheng/font/fontello.woff
Pyqt5ZhongwenJiaocheng/img/__init__.py
Pyqt5ZhongwenJiaocheng/img/annotator-glyph-sprite.png
Pyqt5ZhongwenJiaocheng/img/annotator-icon-sprite.png
Pyqt5ZhongwenJiaocheng/img/apple-touch-icon.png
Pyqt5ZhongwenJiaocheng/img/cancelfullscreen.png
Pyqt5ZhongwenJiaocheng/img/close.png
Pyqt5ZhongwenJiaocheng/img/fullscreen.png
Pyqt5ZhongwenJiaocheng/img/loader.gif
Pyqt5ZhongwenJiaocheng/img/menu-icon.png
Pyqt5ZhongwenJiaocheng/img/save.png
Pyqt5ZhongwenJiaocheng/img/saved.png
Pyqt5ZhongwenJiaocheng/img/settings-s.png
Pyqt5ZhongwenJiaocheng/img/settings.png
Pyqt5ZhongwenJiaocheng/img/star.png
Pyqt5ZhongwenJiaocheng/js/__init__.py
Pyqt5ZhongwenJiaocheng/js/epub.js
Pyqt5ZhongwenJiaocheng/js/epub.min.js
Pyqt5ZhongwenJiaocheng/js/epub.min.map
Pyqt5ZhongwenJiaocheng/js/hooks.min.js
Pyqt5ZhongwenJiaocheng/js/hooks.min.map
Pyqt5ZhongwenJiaocheng/js/reader.js
Pyqt5ZhongwenJiaocheng/js/reader.js.map
Pyqt5ZhongwenJiaocheng/js/reader.min.js
Pyqt5ZhongwenJiaocheng/js/reader.min.map
Pyqt5ZhongwenJiaocheng/js/hooks/__init__.py
Pyqt5ZhongwenJiaocheng/js/hooks/extensions/__init__.py
Pyqt5ZhongwenJiaocheng/js/hooks/extensions/highlight.js
Pyqt5ZhongwenJiaocheng/js/libs/__init__.py
Pyqt5ZhongwenJiaocheng/js/libs/jquery.min.js
Pyqt5ZhongwenJiaocheng/js/libs/localforage.min.js
Pyqt5ZhongwenJiaocheng/js/libs/screenfull.js
Pyqt5ZhongwenJiaocheng/js/libs/screenfull.min.js
Pyqt5ZhongwenJiaocheng/js/libs/zip.min.js
pyqt5_zhongwen_jiaocheng-2024.3.4.0.dist-info/METADATA
pyqt5_zhongwen_jiaocheng-2024.3.4.0.dist-info/WHEEL
pyqt5_zhongwen_jiaocheng-2024.3.4.0.dist-info/entry_points.txt
pyqt5_zhongwen_jiaocheng-2024.3.4.0.dist-info/top_level.txt
pyqt5_zhongwen_jiaocheng-2024.3.4.0.dist-info/RECORD
